rsrpc/json.py
rsrpc/jsonrpc.py
rsrpc-0.1.0.dist-info/LICENSE
rsrpc-0.1.0.dist-info/METADATA
rsrpc-0.1.0.dist-info/WHEEL
rsrpc-0.1.0.dist-info/top_level.txt
rsrpc-0.1.0.dist-info/RECORD
