Metadata-Version: 2.1
Name: rsrpc
Version: 0.1.0
License-File: LICENSE
Provides-Extra: jsonrpc
Requires-Dist: requests ; extra == 'jsonrpc'
